[
  {
    "name": "Nike Air Max Portal Total Black",
    "price_usd": 100,
    "old_price_usd": 165,
    "url": "https://sneakers.com.ua/usi-tovary/nike-air-max-portal-total-black",
    "slug": "nike-air-max-portal-total-black",
    "groupSlug": "nike-air-max-portal-total",
    "appearance_en": "Зовні: взуття виконано з текстилю та синтетики; Всередині: м яка текстильна підкладка, дихаюча устілка; Підошва: з піноматеріалу, резина, повітряні подушки Air; Сезонність: універсальна; Виробник: В єтнам; Ми дуже цінуємо Ваш час і тому зібрали добірку найпоширеніших питань і відповіді на них:  Доставка/оплата? Кросівки доставляються через «Нову Пошту» наложкою. Середній час доставки нашого магазину 1–3 дні. Самовивозу немає! Оплата відбувається після примірки взуття, іноді ми можемо попросити н",
    "images_local": [
      "/products/sneakers/nike_air_max_portal_total_black/1.png",
      "/products/sneakers/nike_air_max_portal_total_black/2.png",
      "/products/sneakers/nike_air_max_portal_total_black/3.png",
      "/products/sneakers/nike_air_max_portal_total_black/4.png",
      "/products/sneakers/nike_air_max_portal_total_black/5.png"
    ],
    "sizes": [
      {
        "eur_size": 35.0,
        "cm_size": 23.3
      },
      {
        "eur_size": 35.5,
        "cm_size": 23.7
      },
      {
        "eur_size": 36.0,
        "cm_size": 23.0
      },
      {
        "eur_size": 36.5,
        "cm_size": 23.0
      },
      {
        "eur_size": 37.0,
        "cm_size": 23.5
      },
      {
        "eur_size": 37.5,
        "cm_size": 23.5
      },
      {
        "eur_size": 38.0,
        "cm_size": 24.0
      },
      {
        "eur_size": 38.5,
        "cm_size": 24.0
      },
      {
        "eur_size": 39.0,
        "cm_size": 25.0
      },
      {
        "eur_size": 40.0,
        "cm_size": 25.5
      },
      {
        "eur_size": 41.0,
        "cm_size": 26.0
      },
      {
        "eur_size": 42.0,
        "cm_size": 26.5
      },
      {
        "eur_size": 42.5,
        "cm_size": 26.5
      },
      {
        "eur_size": 43.0,
        "cm_size": 27.5
      },
      {
        "eur_size": 44.0,
        "cm_size": 28.0
      },
      {
        "eur_size": 44.5,
        "cm_size": 28.0
      },
      {
        "eur_size": 45.0,
        "cm_size": 29.0
      },
      {
        "eur_size": 45.5,
        "cm_size": 29.0
      },
      {
        "eur_size": 46.0,
        "cm_size": 29.5
      },
      {
        "eur_size": 46.5,
        "cm_size": 29.5
      },
      {
        "eur_size": 47.0,
        "cm_size": 30.0
      },
      {
        "eur_size": 47.5,
        "cm_size": 30.0
      },
      {
        "eur_size": 48.0,
        "cm_size": 30.5
      },
      {
        "eur_size": 48.5,
        "cm_size": 30.5
      },
      {
        "eur_size": 49.0,
        "cm_size": 32.7
      },
      {
        "eur_size": 49.5,
        "cm_size": 33.0
      }
    ]
  },
  {
    "name": "New Balance 9060 Dark Grey",
    "price_usd": 93,
    "old_price_usd": 160,
    "url": "https://sneakers.com.ua/usi-tovary/new-balance-9060-dark-grey",
    "slug": "new-balance-9060-dark-grey",
    "groupSlug": "new-balance-9060",
    "appearance_en": "Шкіра, замша, текстиль.  New Balance 9060 — ці кросівки є стильним і функціональним взуттям, яке поєднує в собі сучасний дизайн і передові технології. Вони є одними з нових моделей від всесвітньо відомого бренду New Balance, який славиться своєю якістю та комфортом. New Balance 9060 — це взуття, розроблене для тих, хто цінує комфорт, якість та стиль. Вони ідеально підходять для будь-якої активності, від спорту до повсякденного життя. Якщо Ви шукаєте надійну та сучасну пару кросівок, New Balance ",
    "images_local": [
      "/products/sneakers/new_balance_9060_dark_grey/1.png",
      "/products/sneakers/new_balance_9060_dark_grey/2.png",
      "/products/sneakers/new_balance_9060_dark_grey/3.png",
      "/products/sneakers/new_balance_9060_dark_grey/4.png",
      "/products/sneakers/new_balance_9060_dark_grey/5.png"
    ],
    "sizes": [
      {
        "eur_size": 35.0,
        "cm_size": 23.3
      },
      {
        "eur_size": 35.5,
        "cm_size": 23.7
      },
      {
        "eur_size": 36.0,
        "cm_size": 23.0
      },
      {
        "eur_size": 36.5,
        "cm_size": 23.0
      },
      {
        "eur_size": 37.0,
        "cm_size": 23.5
      },
      {
        "eur_size": 37.5,
        "cm_size": 23.5
      },
      {
        "eur_size": 38.0,
        "cm_size": 24.0
      },
      {
        "eur_size": 38.5,
        "cm_size": 24.0
      },
      {
        "eur_size": 39.0,
        "cm_size": 25.0
      },
      {
        "eur_size": 40.0,
        "cm_size": 25.5
      },
      {
        "eur_size": 41.0,
        "cm_size": 26.0
      },
      {
        "eur_size": 42.0,
        "cm_size": 26.5
      },
      {
        "eur_size": 42.5,
        "cm_size": 26.5
      },
      {
        "eur_size": 43.0,
        "cm_size": 27.5
      },
      {
        "eur_size": 44.0,
        "cm_size": 28.0
      },
      {
        "eur_size": 44.5,
        "cm_size": 28.0
      },
      {
        "eur_size": 45.0,
        "cm_size": 29.0
      },
      {
        "eur_size": 45.5,
        "cm_size": 29.0
      },
      {
        "eur_size": 46.0,
        "cm_size": 29.5
      },
      {
        "eur_size": 46.5,
        "cm_size": 29.5
      },
      {
        "eur_size": 47.0,
        "cm_size": 30.0
      },
      {
        "eur_size": 47.5,
        "cm_size": 30.0
      },
      {
        "eur_size": 48.0,
        "cm_size": 30.5
      },
      {
        "eur_size": 48.5,
        "cm_size": 30.5
      },
      {
        "eur_size": 49.0,
        "cm_size": 32.7
      },
      {
        "eur_size": 49.5,
        "cm_size": 33.0
      }
    ]
  },
  {
    "name": "Adidas Niteball Silver Metallic H67360",
    "price_usd": 83,
    "old_price_usd": 167,
    "url": "https://sneakers.com.ua/usi-tovary/adidas-niteball-silver-metallic-h67360",
    "slug": "adidas-niteball-silver-metallic-h67360",
    "groupSlug": "adidas-niteball-silver-metallic-h67360",
    "appearance_en": "Зовні: верхня частина з шкіри, синтетики та фірмового текстилю за технологією adidas Primeknit (тканина містить не менше 50% Parley Ocean Plastic та 50% переробленого поліестеру) — забезпечить неперевершений комфорт, чудову вентиляцію ніг та неймовірну надійність і довговічність взуття, мають вставки з шкіри та сітки; Всередині: м яка текстильна підкладка, анатомічна дихаюча устілка та фіксація пʼятки; Підошва: має відмінну амортизацію та зчеплення. Вона виготовлена з міцних та гнучких матеріалі",
    "images_local": [
      "/products/sneakers/adidas_niteball_silver_metallic_h67360/1.png",
      "/products/sneakers/adidas_niteball_silver_metallic_h67360/2.png",
      "/products/sneakers/adidas_niteball_silver_metallic_h67360/3.png",
      "/products/sneakers/adidas_niteball_silver_metallic_h67360/4.png",
      "/products/sneakers/adidas_niteball_silver_metallic_h67360/5.png",
      "/products/sneakers/adidas_niteball_silver_metallic_h67360/6.png"
    ],
    "sizes": [
      {
        "eur_size": 35.0,
        "cm_size": 23.3
      },
      {
        "eur_size": 35.5,
        "cm_size": 23.7
      },
      {
        "eur_size": 36.0,
        "cm_size": 23.0
      },
      {
        "eur_size": 36.5,
        "cm_size": 23.0
      },
      {
        "eur_size": 37.0,
        "cm_size": 23.5
      },
      {
        "eur_size": 37.5,
        "cm_size": 23.5
      },
      {
        "eur_size": 38.0,
        "cm_size": 24.0
      },
      {
        "eur_size": 38.5,
        "cm_size": 24.0
      },
      {
        "eur_size": 39.0,
        "cm_size": 25.0
      },
      {
        "eur_size": 40.0,
        "cm_size": 25.5
      },
      {
        "eur_size": 41.0,
        "cm_size": 26.0
      },
      {
        "eur_size": 42.0,
        "cm_size": 26.5
      },
      {
        "eur_size": 42.5,
        "cm_size": 26.5
      },
      {
        "eur_size": 43.0,
        "cm_size": 27.5
      },
      {
        "eur_size": 44.0,
        "cm_size": 28.0
      },
      {
        "eur_size": 44.5,
        "cm_size": 28.0
      },
      {
        "eur_size": 45.0,
        "cm_size": 29.0
      },
      {
        "eur_size": 45.5,
        "cm_size": 29.0
      },
      {
        "eur_size": 46.0,
        "cm_size": 29.5
      },
      {
        "eur_size": 46.5,
        "cm_size": 29.5
      },
      {
        "eur_size": 47.0,
        "cm_size": 30.0
      },
      {
        "eur_size": 47.5,
        "cm_size": 30.0
      },
      {
        "eur_size": 48.0,
        "cm_size": 30.5
      },
      {
        "eur_size": 48.5,
        "cm_size": 30.5
      },
      {
        "eur_size": 49.0,
        "cm_size": 32.7
      },
      {
        "eur_size": 49.5,
        "cm_size": 33.0
      }
    ]
  },
  {
    "name": "Nike Vomero Roam Black FV2295-002",
    "price_usd": 100,
    "old_price_usd": 189,
    "url": "https://sneakers.com.ua/usi-tovary/nike-vomero-roam-black-fv2295-002",
    "slug": "nike-vomero-roam-black-fv2295-002",
    "groupSlug": "nike-vomero-roam-black-fv2295-002",
    "appearance_en": "Зовні: верхня частина взуття виконана з міцного текстилю та синтетики, забезпечуючи хорошу вентиляцію та підтримку ноги. Це дозволяє ногам дихати і знижує ризик появи неприємних відчуттів чи подразнень; Всередині: м’яка текстильна підкладка, дихаюча устілка; Підошва: Zoom Vomero має протектор з гарною зчеплюваністю та зносостійкістю, що робить їх придатними для використання на різних поверхнях. Вони забезпечують стабільність та підтримку стопи; Сезонність: універсальна; Виробник: В’єтнам.  Доста",
    "images_local": [
      "/products/sneakers/nike_vomero_roam_black_fv2295_002/1.png",
      "/products/sneakers/nike_vomero_roam_black_fv2295_002/2.png",
      "/products/sneakers/nike_vomero_roam_black_fv2295_002/3.png",
      "/products/sneakers/nike_vomero_roam_black_fv2295_002/4.png",
      "/products/sneakers/nike_vomero_roam_black_fv2295_002/5.png"
    ],
    "sizes": [
      {
        "eur_size": 35.0,
        "cm_size": 23.3
      },
      {
        "eur_size": 35.5,
        "cm_size": 23.7
      },
      {
        "eur_size": 36.0,
        "cm_size": 23.0
      },
      {
        "eur_size": 36.5,
        "cm_size": 23.0
      },
      {
        "eur_size": 37.0,
        "cm_size": 23.5
      },
      {
        "eur_size": 37.5,
        "cm_size": 23.5
      },
      {
        "eur_size": 38.0,
        "cm_size": 24.0
      },
      {
        "eur_size": 38.5,
        "cm_size": 24.0
      },
      {
        "eur_size": 39.0,
        "cm_size": 25.0
      },
      {
        "eur_size": 40.0,
        "cm_size": 25.5
      },
      {
        "eur_size": 41.0,
        "cm_size": 26.0
      },
      {
        "eur_size": 42.0,
        "cm_size": 26.5
      },
      {
        "eur_size": 42.5,
        "cm_size": 26.5
      },
      {
        "eur_size": 43.0,
        "cm_size": 27.5
      },
      {
        "eur_size": 44.0,
        "cm_size": 28.0
      },
      {
        "eur_size": 44.5,
        "cm_size": 28.0
      },
      {
        "eur_size": 45.0,
        "cm_size": 29.0
      },
      {
        "eur_size": 45.5,
        "cm_size": 29.0
      },
      {
        "eur_size": 46.0,
        "cm_size": 29.5
      },
      {
        "eur_size": 46.5,
        "cm_size": 29.5
      },
      {
        "eur_size": 47.0,
        "cm_size": 30.0
      },
      {
        "eur_size": 47.5,
        "cm_size": 30.0
      },
      {
        "eur_size": 48.0,
        "cm_size": 30.5
      },
      {
        "eur_size": 48.5,
        "cm_size": 30.5
      },
      {
        "eur_size": 49.0,
        "cm_size": 32.7
      },
      {
        "eur_size": 49.5,
        "cm_size": 33.0
      }
    ]
  },
  {
    "name": "New Balance 1906A Black Dragon Berry U1906AD",
    "price_usd": 90,
    "old_price_usd": 162,
    "url": "https://sneakers.com.ua/usi-tovary/new-balance-1906a-black-dragon-berry-u1906ad",
    "slug": "new-balance-1906a-black-dragon-berry-u1906ad",
    "groupSlug": "new-balance-1906a-black-dragon-berry-u1906ad",
    "appearance_en": "Шкіра, текстиль, синтетика.  Кросівки New Balance 1906 — це преміальна модель взуття, яка поєднує класичний дизайн і передові технології. Модель 1906 — є елегантними та стильними кросівками, створеними для комфорту та підтримки протягом дня. Вони ідеально підходять для повсякденного носіння або для створення стильного та елегантного образу. Вони легко поєднуються з різними стилями одягу, від класичних до спортивних, і підходять для будь-яких сезонів. Якщо Ви шукаєте кросівки, які поєднують у соб",
    "images_local": [
      "/products/sneakers/new_balance_1906a_black_dragon_berry_u1906ad/1.png",
      "/products/sneakers/new_balance_1906a_black_dragon_berry_u1906ad/2.png",
      "/products/sneakers/new_balance_1906a_black_dragon_berry_u1906ad/3.png",
      "/products/sneakers/new_balance_1906a_black_dragon_berry_u1906ad/4.png",
      "/products/sneakers/new_balance_1906a_black_dragon_berry_u1906ad/5.png"
    ],
    "sizes": [
      {
        "eur_size": 35.0,
        "cm_size": 23.3
      },
      {
        "eur_size": 35.5,
        "cm_size": 23.7
      },
      {
        "eur_size": 36.0,
        "cm_size": 23.0
      },
      {
        "eur_size": 36.5,
        "cm_size": 23.0
      },
      {
        "eur_size": 37.0,
        "cm_size": 23.5
      },
      {
        "eur_size": 37.5,
        "cm_size": 23.5
      },
      {
        "eur_size": 38.0,
        "cm_size": 24.0
      },
      {
        "eur_size": 38.5,
        "cm_size": 24.0
      },
      {
        "eur_size": 39.0,
        "cm_size": 25.0
      },
      {
        "eur_size": 40.0,
        "cm_size": 25.5
      },
      {
        "eur_size": 41.0,
        "cm_size": 26.0
      },
      {
        "eur_size": 42.0,
        "cm_size": 26.5
      },
      {
        "eur_size": 42.5,
        "cm_size": 26.5
      },
      {
        "eur_size": 43.0,
        "cm_size": 27.5
      },
      {
        "eur_size": 44.0,
        "cm_size": 28.0
      },
      {
        "eur_size": 44.5,
        "cm_size": 28.0
      },
      {
        "eur_size": 45.0,
        "cm_size": 29.0
      },
      {
        "eur_size": 45.5,
        "cm_size": 29.0
      },
      {
        "eur_size": 46.0,
        "cm_size": 29.5
      },
      {
        "eur_size": 46.5,
        "cm_size": 29.5
      },
      {
        "eur_size": 47.0,
        "cm_size": 30.0
      },
      {
        "eur_size": 47.5,
        "cm_size": 30.0
      },
      {
        "eur_size": 48.0,
        "cm_size": 30.5
      },
      {
        "eur_size": 48.5,
        "cm_size": 30.5
      },
      {
        "eur_size": 49.0,
        "cm_size": 32.7
      },
      {
        "eur_size": 49.5,
        "cm_size": 33.0
      }
    ]
  },
  {
    "name": "Nike Air Force 1 Low x Supreme Beige Blue",
    "price_usd": 107,
    "old_price_usd": 163,
    "url": "https://sneakers.com.ua/usi-tovary/nike-air-force-1-low-x-supreme-beige-blue",
    "slug": "nike-air-force-1-low-x-supreme-beige-blue",
    "groupSlug": "nike-air-force-1-low-x-supreme",
    "appearance_en": "класика та надійність, асболютно зносостійка шкіра та міцна строчка, за взуттям легко доглядати, кросівки дуже живучі. Підійдуть підь будь-який гардероб, відрізняються підвищенним комфортом. Удосконалений дизайн та покращена якість дозволяють використовувати air force будь-де: для спорту, для щоденних прогулянок, для баскетболу чи скейтбордингу, для чоловіків та для жінок, для молоді та для літніх людей — ці форси реально найкращі у світі.",
    "images_local": [
      "/products/sneakers/nike_air_force_1_low_x_supreme_beige_blue/1.png",
      "/products/sneakers/nike_air_force_1_low_x_supreme_beige_blue/2.png",
      "/products/sneakers/nike_air_force_1_low_x_supreme_beige_blue/3.png",
      "/products/sneakers/nike_air_force_1_low_x_supreme_beige_blue/4.png",
      "/products/sneakers/nike_air_force_1_low_x_supreme_beige_blue/5.png",
      "/products/sneakers/nike_air_force_1_low_x_supreme_beige_blue/6.png"
    ],
    "sizes": [
      {
        "eur_size": 35.0,
        "cm_size": 23.3
      },
      {
        "eur_size": 35.5,
        "cm_size": 23.7
      },
      {
        "eur_size": 36.0,
        "cm_size": 23.0
      },
      {
        "eur_size": 36.5,
        "cm_size": 23.0
      },
      {
        "eur_size": 37.0,
        "cm_size": 23.5
      },
      {
        "eur_size": 37.5,
        "cm_size": 23.5
      },
      {
        "eur_size": 38.0,
        "cm_size": 24.0
      },
      {
        "eur_size": 38.5,
        "cm_size": 24.0
      },
      {
        "eur_size": 39.0,
        "cm_size": 25.0
      },
      {
        "eur_size": 40.0,
        "cm_size": 25.5
      },
      {
        "eur_size": 41.0,
        "cm_size": 26.0
      },
      {
        "eur_size": 42.0,
        "cm_size": 26.5
      },
      {
        "eur_size": 42.5,
        "cm_size": 26.5
      },
      {
        "eur_size": 43.0,
        "cm_size": 27.5
      },
      {
        "eur_size": 44.0,
        "cm_size": 28.0
      },
      {
        "eur_size": 44.5,
        "cm_size": 28.0
      },
      {
        "eur_size": 45.0,
        "cm_size": 29.0
      },
      {
        "eur_size": 45.5,
        "cm_size": 29.0
      },
      {
        "eur_size": 46.0,
        "cm_size": 29.5
      },
      {
        "eur_size": 46.5,
        "cm_size": 29.5
      },
      {
        "eur_size": 47.0,
        "cm_size": 30.0
      },
      {
        "eur_size": 47.5,
        "cm_size": 30.0
      },
      {
        "eur_size": 48.0,
        "cm_size": 30.5
      },
      {
        "eur_size": 48.5,
        "cm_size": 30.5
      },
      {
        "eur_size": 49.0,
        "cm_size": 32.7
      },
      {
        "eur_size": 49.5,
        "cm_size": 33.0
      }
    ]
  },
  {
    "name": "Nike Dunk Low Retro White Black DD1391-100",
    "price_usd": 86,
    "old_price_usd": 115,
    "url": "https://sneakers.com.ua/usi-tovary/dunk-low-retro-white-black-dd1391-100",
    "slug": "nike-dunk-low-retro-white-black-dd1391-100",
    "groupSlug": "nike-dunk-low-retro-white-black-dd1391-100",
    "appearance_en": "Зовні: взуття виконано з міцної шкіри, скрізь присутня строчка, а в області носка — перфорація для вентиляції! Силует кросівок нагадує класичні баскетбольні моделі з 80-их, але тепер вони поєднанні із найсучаснішими технологіями снікер індустрії; Всередині: м яка текстильна підкладка, анатомічна дихаюча устілка; Підошва: з піноматеріалу, прихований балон для амортизації за технологією Zoom Air гарантує комфорт та безпеку, підошви прошиті та проклеєні за сучасними технологіями із використанням ви",
    "images_local": [
      "/products/sneakers/nike_dunk_low_retro_white_black_dd1391_100/1.png",
      "/products/sneakers/nike_dunk_low_retro_white_black_dd1391_100/2.png",
      "/products/sneakers/nike_dunk_low_retro_white_black_dd1391_100/3.png",
      "/products/sneakers/nike_dunk_low_retro_white_black_dd1391_100/4.png",
      "/products/sneakers/nike_dunk_low_retro_white_black_dd1391_100/5.png",
      "/products/sneakers/nike_dunk_low_retro_white_black_dd1391_100/6.png"
    ],
    "sizes": [
      {
        "eur_size": 35.0,
        "cm_size": 23.3
      },
      {
        "eur_size": 35.5,
        "cm_size": 23.7
      },
      {
        "eur_size": 36.0,
        "cm_size": 23.0
      },
      {
        "eur_size": 36.5,
        "cm_size": 23.0
      },
      {
        "eur_size": 37.0,
        "cm_size": 23.5
      },
      {
        "eur_size": 37.5,
        "cm_size": 23.5
      },
      {
        "eur_size": 38.0,
        "cm_size": 24.0
      },
      {
        "eur_size": 38.5,
        "cm_size": 24.0
      },
      {
        "eur_size": 39.0,
        "cm_size": 25.0
      },
      {
        "eur_size": 40.0,
        "cm_size": 25.5
      },
      {
        "eur_size": 41.0,
        "cm_size": 26.0
      },
      {
        "eur_size": 42.0,
        "cm_size": 26.5
      },
      {
        "eur_size": 42.5,
        "cm_size": 26.5
      },
      {
        "eur_size": 43.0,
        "cm_size": 27.5
      },
      {
        "eur_size": 44.0,
        "cm_size": 28.0
      },
      {
        "eur_size": 44.5,
        "cm_size": 28.0
      },
      {
        "eur_size": 45.0,
        "cm_size": 29.0
      },
      {
        "eur_size": 45.5,
        "cm_size": 29.0
      },
      {
        "eur_size": 46.0,
        "cm_size": 29.5
      },
      {
        "eur_size": 46.5,
        "cm_size": 29.5
      },
      {
        "eur_size": 47.0,
        "cm_size": 30.0
      },
      {
        "eur_size": 47.5,
        "cm_size": 30.0
      },
      {
        "eur_size": 48.0,
        "cm_size": 30.5
      },
      {
        "eur_size": 48.5,
        "cm_size": 30.5
      },
      {
        "eur_size": 49.0,
        "cm_size": 32.7
      },
      {
        "eur_size": 49.5,
        "cm_size": 33.0
      }
    ]
  },
  {
    "name": "Adidas Campus Aluminium Black HQ8711",
    "price_usd": 83,
    "old_price_usd": 173,
    "url": "https://sneakers.com.ua/usi-tovary/campus-aluminium-black-hq8711",
    "slug": "adidas-campus-aluminium-black-hq8711",
    "groupSlug": "adidas-campus-aluminium-black-hq8711",
    "appearance_en": "Зовні: Adidas Campus має елегантний та класичний дизайн. Верх виготовлений з міцного матеріалу високої якості, що надає взуттю стильний вигляд. Деталі у вигляді трьох смуг бренду Adidas на боковій частині взуття додають додатковий акцент та впізнаваність; Всередині: Adidas Campus забезпечує комфорт та підтримку під час носіння. М яка підкладка та устілка забезпечують додатковий комфорт та амортизацію. Внутрішні матеріали високої якості забезпечують хорошу вентиляцію та запобігають появі",
    "images_local": [
      "/products/sneakers/adidas_campus_aluminium_black_hq8711/1.png",
      "/products/sneakers/adidas_campus_aluminium_black_hq8711/2.png",
      "/products/sneakers/adidas_campus_aluminium_black_hq8711/3.png",
      "/products/sneakers/adidas_campus_aluminium_black_hq8711/4.png",
      "/products/sneakers/adidas_campus_aluminium_black_hq8711/5.png"
    ],
    "sizes": [
      {
        "eur_size": 35.0,
        "cm_size": 23.3
      },
      {
        "eur_size": 35.5,
        "cm_size": 23.7
      },
      {
        "eur_size": 36.0,
        "cm_size": 23.0
      },
      {
        "eur_size": 36.5,
        "cm_size": 23.0
      },
      {
        "eur_size": 37.0,
        "cm_size": 23.5
      },
      {
        "eur_size": 37.5,
        "cm_size": 23.5
      },
      {
        "eur_size": 38.0,
        "cm_size": 24.0
      },
      {
        "eur_size": 38.5,
        "cm_size": 24.0
      },
      {
        "eur_size": 39.0,
        "cm_size": 25.0
      },
      {
        "eur_size": 40.0,
        "cm_size": 25.5
      },
      {
        "eur_size": 41.0,
        "cm_size": 26.0
      },
      {
        "eur_size": 42.0,
        "cm_size": 26.5
      },
      {
        "eur_size": 42.5,
        "cm_size": 26.5
      },
      {
        "eur_size": 43.0,
        "cm_size": 27.5
      },
      {
        "eur_size": 44.0,
        "cm_size": 28.0
      },
      {
        "eur_size": 44.5,
        "cm_size": 28.0
      },
      {
        "eur_size": 45.0,
        "cm_size": 29.0
      },
      {
        "eur_size": 45.5,
        "cm_size": 29.0
      },
      {
        "eur_size": 46.0,
        "cm_size": 29.5
      },
      {
        "eur_size": 46.5,
        "cm_size": 29.5
      },
      {
        "eur_size": 47.0,
        "cm_size": 30.0
      },
      {
        "eur_size": 47.5,
        "cm_size": 30.0
      },
      {
        "eur_size": 48.0,
        "cm_size": 30.5
      },
      {
        "eur_size": 48.5,
        "cm_size": 30.5
      },
      {
        "eur_size": 49.0,
        "cm_size": 32.7
      },
      {
        "eur_size": 49.5,
        "cm_size": 33.0
      }
    ]
  },
  {
    "name": "Jordan Spizike Low Archaeo Brown FQ1759-101",
    "price_usd": 109,
    "old_price_usd": 182,
    "url": "https://sneakers.com.ua/usi-tovary/jordan-spizike-low-archaeo-brown-fq1759-101",
    "slug": "jordan-spizike-low-archaeo-brown-fq1759-101",
    "groupSlug": "jordan-spizike-low-archaeo-brown-fq1759-101",
    "appearance_en": "Зовні: взуття виконано з шкіри, присутні синтетичні вставки для безгоданної вентиляції Ваших ніг; Всередині: м яка текстильна підкладка, дихаюча устілка; Підошва: з піноматеріалу, балон для амортизації за технологією Air-Sole в області п ятки. Резинова підмітка з чіпким візерунком протектора; Сезонність: універсальна; Виробник: В єтнам; Доставка: наложка «Нова Пошта», доставка кросівок Джордан за 1-2 доби. Самовивозу НЕМАЄ; Оплата: при отриманні, після огляду та примірки взуття будь-яким зручним",
    "images_local": [
      "/products/sneakers/jordan_spizike_low_archaeo_brown_fq1759_101/1.png",
      "/products/sneakers/jordan_spizike_low_archaeo_brown_fq1759_101/2.png",
      "/products/sneakers/jordan_spizike_low_archaeo_brown_fq1759_101/3.png",
      "/products/sneakers/jordan_spizike_low_archaeo_brown_fq1759_101/4.png",
      "/products/sneakers/jordan_spizike_low_archaeo_brown_fq1759_101/5.png"
    ],
    "sizes": [
      {
        "eur_size": 35.0,
        "cm_size": 23.3
      },
      {
        "eur_size": 35.5,
        "cm_size": 23.7
      },
      {
        "eur_size": 36.0,
        "cm_size": 23.0
      },
      {
        "eur_size": 36.5,
        "cm_size": 23.0
      },
      {
        "eur_size": 37.0,
        "cm_size": 23.5
      },
      {
        "eur_size": 37.5,
        "cm_size": 23.5
      },
      {
        "eur_size": 38.0,
        "cm_size": 24.0
      },
      {
        "eur_size": 38.5,
        "cm_size": 24.0
      },
      {
        "eur_size": 39.0,
        "cm_size": 25.0
      },
      {
        "eur_size": 40.0,
        "cm_size": 25.5
      },
      {
        "eur_size": 41.0,
        "cm_size": 26.0
      },
      {
        "eur_size": 42.0,
        "cm_size": 26.5
      },
      {
        "eur_size": 42.5,
        "cm_size": 26.5
      },
      {
        "eur_size": 43.0,
        "cm_size": 27.5
      },
      {
        "eur_size": 44.0,
        "cm_size": 28.0
      },
      {
        "eur_size": 44.5,
        "cm_size": 28.0
      },
      {
        "eur_size": 45.0,
        "cm_size": 29.0
      },
      {
        "eur_size": 45.5,
        "cm_size": 29.0
      },
      {
        "eur_size": 46.0,
        "cm_size": 29.5
      },
      {
        "eur_size": 46.5,
        "cm_size": 29.5
      },
      {
        "eur_size": 47.0,
        "cm_size": 30.0
      },
      {
        "eur_size": 47.5,
        "cm_size": 30.0
      },
      {
        "eur_size": 48.0,
        "cm_size": 30.5
      },
      {
        "eur_size": 48.5,
        "cm_size": 30.5
      },
      {
        "eur_size": 49.0,
        "cm_size": 32.7
      },
      {
        "eur_size": 49.5,
        "cm_size": 33.0
      }
    ]
  },
  {
    "name": "Nike Air Force 1 Low x DOAF Oregon Duck or Egg IU7612-700",
    "price_usd": 107,
    "old_price_usd": 165,
    "url": "https://sneakers.com.ua/usi-tovary/nike-air-force-1-low-x-doaf-oregon-duck-or-egg-iu7612-700",
    "slug": "nike-air-force-1-low-x-doaf-oregon-duck-or-egg-iu7612-700",
    "groupSlug": "nike-air-force-1-low-x-doaf-oregon-duck-or-egg-iu7612-700",
    "appearance_en": "класика та надійність, асболютно зносостійка шкіра та міцна строчка, за взуттям легко доглядати, кросівки дуже живучі. Підійдуть підь будь-який гардероб, відрізняються підвищенним комфортом. Удосконалений дизайн та покращена якість дозволяють використовувати air force будь-де: для спорту, для щоденних прогулянок, для баскетболу чи скейтбордингу, для чоловіків та для жінок, для молоді та для літніх людей — ці форси реально найкращі у світі.",
    "images_local": [
      "/products/sneakers/nike_air_force_1_low_x_doaf_oregon_duck_or_egg_iu7612_700/1.png",
      "/products/sneakers/nike_air_force_1_low_x_doaf_oregon_duck_or_egg_iu7612_700/2.png",
      "/products/sneakers/nike_air_force_1_low_x_doaf_oregon_duck_or_egg_iu7612_700/3.png",
      "/products/sneakers/nike_air_force_1_low_x_doaf_oregon_duck_or_egg_iu7612_700/4.png",
      "/products/sneakers/nike_air_force_1_low_x_doaf_oregon_duck_or_egg_iu7612_700/5.png",
      "/products/sneakers/nike_air_force_1_low_x_doaf_oregon_duck_or_egg_iu7612_700/6.png"
    ],
    "sizes": [
      {
        "eur_size": 35.0,
        "cm_size": 23.3
      },
      {
        "eur_size": 35.5,
        "cm_size": 23.7
      },
      {
        "eur_size": 36.0,
        "cm_size": 23.0
      },
      {
        "eur_size": 36.5,
        "cm_size": 23.0
      },
      {
        "eur_size": 37.0,
        "cm_size": 23.5
      },
      {
        "eur_size": 37.5,
        "cm_size": 23.5
      },
      {
        "eur_size": 38.0,
        "cm_size": 24.0
      },
      {
        "eur_size": 38.5,
        "cm_size": 24.0
      },
      {
        "eur_size": 39.0,
        "cm_size": 25.0
      },
      {
        "eur_size": 40.0,
        "cm_size": 25.5
      },
      {
        "eur_size": 41.0,
        "cm_size": 26.0
      },
      {
        "eur_size": 42.0,
        "cm_size": 26.5
      },
      {
        "eur_size": 42.5,
        "cm_size": 26.5
      },
      {
        "eur_size": 43.0,
        "cm_size": 27.5
      },
      {
        "eur_size": 44.0,
        "cm_size": 28.0
      },
      {
        "eur_size": 44.5,
        "cm_size": 28.0
      },
      {
        "eur_size": 45.0,
        "cm_size": 29.0
      },
      {
        "eur_size": 45.5,
        "cm_size": 29.0
      },
      {
        "eur_size": 46.0,
        "cm_size": 29.5
      },
      {
        "eur_size": 46.5,
        "cm_size": 29.5
      },
      {
        "eur_size": 47.0,
        "cm_size": 30.0
      },
      {
        "eur_size": 47.5,
        "cm_size": 30.0
      },
      {
        "eur_size": 48.0,
        "cm_size": 30.5
      },
      {
        "eur_size": 48.5,
        "cm_size": 30.5
      },
      {
        "eur_size": 49.0,
        "cm_size": 32.7
      },
      {
        "eur_size": 49.5,
        "cm_size": 33.0
      }
    ]
  },
  {
    "name": "New Balance 2002R Protection Pack Rain Cloud M2002RDA",
    "price_usd": 95,
    "old_price_usd": 123,
    "url": "https://sneakers.com.ua/usi-tovary/new-balance-2002r-protection-pack-rain-cloud-m2002rda",
    "slug": "new-balance-2002r-protection-pack-rain-cloud-m2002rda",
    "groupSlug": "new-balance-2002r-protection-pack-rain-cloud-m2002rda",
    "appearance_en": "Шкіра, текстиль, синтетика.  Це модернізована версія кросівок 2010 року, зроблена із якісних матеріалів та покращена у декілька разів. Система ABZORB надає зручності у ходьбі через здатність поглинати удари.  New balance 2002R — це ретро-стиль та унікальність, якої прагнуть усі. Самовивозу або шоуруму немає. Виключно онлайн-магазин!  Відправка ТІЛЬКИ «Новою Поштою» протягом 1-2 днів з моменту оформлення замовлення.  Наложений платіж. Часткова передоплата потрібна тільки у разі доставки товару «п",
    "images_local": [
      "/products/sneakers/new_balance_2002r_protection_pack_rain_cloud_m2002rda/1.png",
      "/products/sneakers/new_balance_2002r_protection_pack_rain_cloud_m2002rda/2.png",
      "/products/sneakers/new_balance_2002r_protection_pack_rain_cloud_m2002rda/3.png",
      "/products/sneakers/new_balance_2002r_protection_pack_rain_cloud_m2002rda/4.png",
      "/products/sneakers/new_balance_2002r_protection_pack_rain_cloud_m2002rda/5.png"
    ],
    "sizes": [
      {
        "eur_size": 35.0,
        "cm_size": 23.3
      },
      {
        "eur_size": 35.5,
        "cm_size": 23.7
      },
      {
        "eur_size": 36.0,
        "cm_size": 23.0
      },
      {
        "eur_size": 36.5,
        "cm_size": 23.0
      },
      {
        "eur_size": 37.0,
        "cm_size": 23.5
      },
      {
        "eur_size": 37.5,
        "cm_size": 23.5
      },
      {
        "eur_size": 38.0,
        "cm_size": 24.0
      },
      {
        "eur_size": 38.5,
        "cm_size": 24.0
      },
      {
        "eur_size": 39.0,
        "cm_size": 25.0
      },
      {
        "eur_size": 40.0,
        "cm_size": 25.5
      },
      {
        "eur_size": 41.0,
        "cm_size": 26.0
      },
      {
        "eur_size": 42.0,
        "cm_size": 26.5
      },
      {
        "eur_size": 42.5,
        "cm_size": 26.5
      },
      {
        "eur_size": 43.0,
        "cm_size": 27.5
      },
      {
        "eur_size": 44.0,
        "cm_size": 28.0
      },
      {
        "eur_size": 44.5,
        "cm_size": 28.0
      },
      {
        "eur_size": 45.0,
        "cm_size": 29.0
      },
      {
        "eur_size": 45.5,
        "cm_size": 29.0
      },
      {
        "eur_size": 46.0,
        "cm_size": 29.5
      },
      {
        "eur_size": 46.5,
        "cm_size": 29.5
      },
      {
        "eur_size": 47.0,
        "cm_size": 30.0
      },
      {
        "eur_size": 47.5,
        "cm_size": 30.0
      },
      {
        "eur_size": 48.0,
        "cm_size": 30.5
      },
      {
        "eur_size": 48.5,
        "cm_size": 30.5
      },
      {
        "eur_size": 49.0,
        "cm_size": 32.7
      },
      {
        "eur_size": 49.5,
        "cm_size": 33.0
      }
    ]
  },
  {
    "name": "Nike Air Zoom ACG Black З ХУТРОМ",
    "price_usd": 100,
    "old_price_usd": 197,
    "url": "https://sneakers.com.ua/usi-tovary/nike-air-zoom-acg-black-with-fur",
    "slug": "nike-air-zoom-acg-black-з-хутром",
    "groupSlug": "nike-air-zoom-acg-black-з-хутром",
    "appearance_en": "Зовні: взуття виконано з синтетичних матеріалів; Всередині: м яка текстильна підкладка, дихаюча устілка, хутро; Підошва: з піноматеріалу, резинова підмітка з чіпким візерунком протектора; Сезонність: Зима; Виробник: В єтнам; Ми дуже цінуємо Ваш час і тому зібрали добірку найпоширеніших питань і відповіді на них:  Доставка/оплата? Кросівки доставляються через «Нову Пошту» наложкою. Середній час доставки нашого магазину 1–3 дні. Самовивозу немає! Оплата відбувається після примірки взуття, іноді ми",
    "images_local": [
      "/products/sneakers/nike_air_zoom_acg_black_з_хутром/1.png",
      "/products/sneakers/nike_air_zoom_acg_black_з_хутром/2.png",
      "/products/sneakers/nike_air_zoom_acg_black_з_хутром/3.png",
      "/products/sneakers/nike_air_zoom_acg_black_з_хутром/4.png",
      "/products/sneakers/nike_air_zoom_acg_black_з_хутром/5.png"
    ],
    "sizes": [
      {
        "eur_size": 35.0,
        "cm_size": 23.3
      },
      {
        "eur_size": 35.5,
        "cm_size": 23.7
      },
      {
        "eur_size": 36.0,
        "cm_size": 23.0
      },
      {
        "eur_size": 36.5,
        "cm_size": 23.0
      },
      {
        "eur_size": 37.0,
        "cm_size": 23.5
      },
      {
        "eur_size": 37.5,
        "cm_size": 23.5
      },
      {
        "eur_size": 38.0,
        "cm_size": 24.0
      },
      {
        "eur_size": 38.5,
        "cm_size": 24.0
      },
      {
        "eur_size": 39.0,
        "cm_size": 25.0
      },
      {
        "eur_size": 40.0,
        "cm_size": 25.5
      },
      {
        "eur_size": 41.0,
        "cm_size": 26.0
      },
      {
        "eur_size": 42.0,
        "cm_size": 26.5
      },
      {
        "eur_size": 42.5,
        "cm_size": 26.5
      },
      {
        "eur_size": 43.0,
        "cm_size": 27.5
      },
      {
        "eur_size": 44.0,
        "cm_size": 28.0
      },
      {
        "eur_size": 44.5,
        "cm_size": 28.0
      },
      {
        "eur_size": 45.0,
        "cm_size": 29.0
      },
      {
        "eur_size": 45.5,
        "cm_size": 29.0
      },
      {
        "eur_size": 46.0,
        "cm_size": 29.5
      },
      {
        "eur_size": 46.5,
        "cm_size": 29.5
      },
      {
        "eur_size": 47.0,
        "cm_size": 30.0
      },
      {
        "eur_size": 47.5,
        "cm_size": 30.0
      },
      {
        "eur_size": 48.0,
        "cm_size": 30.5
      },
      {
        "eur_size": 48.5,
        "cm_size": 30.5
      },
      {
        "eur_size": 49.0,
        "cm_size": 32.7
      },
      {
        "eur_size": 49.5,
        "cm_size": 33.0
      }
    ]
  },
  {
    "name": "Nike Air Max Portal Beige Yellow Black White",
    "price_usd": 100,
    "old_price_usd": 165,
    "url": "https://sneakers.com.ua/usi-tovary/nike-air-max-portal-beige-yellow-black-white",
    "slug": "nike-air-max-portal-beige-yellow-black-white",
    "groupSlug": "nike-air-max-portal",
    "appearance_en": "Зовні: взуття виконано з текстилю та синтетики; Всередині: м яка текстильна підкладка, дихаюча устілка; Підошва: з піноматеріалу, резина, повітряні подушки Air; Сезонність: універсальна; Виробник: В єтнам; Ми дуже цінуємо Ваш час і тому зібрали добірку найпоширеніших питань і відповіді на них:  Доставка/оплата? Кросівки доставляються через «Нову Пошту» наложкою. Середній час доставки нашого магазину 1–3 дні. Самовивозу немає! Оплата відбувається після примірки взуття, іноді ми можемо попросити н",
    "images_local": [
      "/products/sneakers/nike_air_max_portal_beige_yellow_black_white/1.png",
      "/products/sneakers/nike_air_max_portal_beige_yellow_black_white/2.png",
      "/products/sneakers/nike_air_max_portal_beige_yellow_black_white/3.png",
      "/products/sneakers/nike_air_max_portal_beige_yellow_black_white/4.png",
      "/products/sneakers/nike_air_max_portal_beige_yellow_black_white/5.png"
    ],
    "sizes": [
      {
        "eur_size": 35.0,
        "cm_size": 23.3
      },
      {
        "eur_size": 35.5,
        "cm_size": 23.7
      },
      {
        "eur_size": 36.0,
        "cm_size": 23.0
      },
      {
        "eur_size": 36.5,
        "cm_size": 23.0
      },
      {
        "eur_size": 37.0,
        "cm_size": 23.5
      },
      {
        "eur_size": 37.5,
        "cm_size": 23.5
      },
      {
        "eur_size": 38.0,
        "cm_size": 24.0
      },
      {
        "eur_size": 38.5,
        "cm_size": 24.0
      },
      {
        "eur_size": 39.0,
        "cm_size": 25.0
      },
      {
        "eur_size": 40.0,
        "cm_size": 25.5
      },
      {
        "eur_size": 41.0,
        "cm_size": 26.0
      },
      {
        "eur_size": 42.0,
        "cm_size": 26.5
      },
      {
        "eur_size": 42.5,
        "cm_size": 26.5
      },
      {
        "eur_size": 43.0,
        "cm_size": 27.5
      },
      {
        "eur_size": 44.0,
        "cm_size": 28.0
      },
      {
        "eur_size": 44.5,
        "cm_size": 28.0
      },
      {
        "eur_size": 45.0,
        "cm_size": 29.0
      },
      {
        "eur_size": 45.5,
        "cm_size": 29.0
      },
      {
        "eur_size": 46.0,
        "cm_size": 29.5
      },
      {
        "eur_size": 46.5,
        "cm_size": 29.5
      },
      {
        "eur_size": 47.0,
        "cm_size": 30.0
      },
      {
        "eur_size": 47.5,
        "cm_size": 30.0
      },
      {
        "eur_size": 48.0,
        "cm_size": 30.5
      },
      {
        "eur_size": 48.5,
        "cm_size": 30.5
      },
      {
        "eur_size": 49.0,
        "cm_size": 32.7
      },
      {
        "eur_size": 49.5,
        "cm_size": 33.0
      }
    ]
  },
  {
    "name": "Puma Suede XL Dark Myrtle 395205-21",
    "price_usd": 70,
    "old_price_usd": 116,
    "url": "https://sneakers.com.ua/usi-tovary/puma-suede-xl-dark-myrtle-395205-21",
    "slug": "puma-suede-xl-dark-myrtle-395205-21",
    "groupSlug": "puma-suede-xl-dark-myrtle-395205-21",
    "appearance_en": "Зовні: Верх виготовлений з замші; Всередині: М яка підкладка та устілка забезпечують додатковий комфорт та амортизацію. Внутрішні матеріали високої якості забезпечують хорошу вентиляцію та запобігають появі неприємного запаху; Підошва: Підошва з резини має відмінну зчеплюваність з поверхнею і забезпечує хорошу амортизацію. Протектор на підмітці забезпечує гарне тертя та стабільність при ходьбі; Сезонність: може використовуватись протягом всього року в залежності від погодних умов; Виробник: В єт",
    "images_local": [
      "/products/sneakers/puma_suede_xl_dark_myrtle_395205_21/1.png",
      "/products/sneakers/puma_suede_xl_dark_myrtle_395205_21/2.png",
      "/products/sneakers/puma_suede_xl_dark_myrtle_395205_21/3.png",
      "/products/sneakers/puma_suede_xl_dark_myrtle_395205_21/4.png",
      "/products/sneakers/puma_suede_xl_dark_myrtle_395205_21/5.png"
    ],
    "sizes": [
      {
        "eur_size": 35.0,
        "cm_size": 23.3
      },
      {
        "eur_size": 35.5,
        "cm_size": 23.7
      },
      {
        "eur_size": 36.0,
        "cm_size": 23.0
      },
      {
        "eur_size": 36.5,
        "cm_size": 23.0
      },
      {
        "eur_size": 37.0,
        "cm_size": 23.5
      },
      {
        "eur_size": 37.5,
        "cm_size": 23.5
      },
      {
        "eur_size": 38.0,
        "cm_size": 24.0
      },
      {
        "eur_size": 38.5,
        "cm_size": 24.0
      },
      {
        "eur_size": 39.0,
        "cm_size": 25.0
      },
      {
        "eur_size": 40.0,
        "cm_size": 25.5
      },
      {
        "eur_size": 41.0,
        "cm_size": 26.0
      },
      {
        "eur_size": 42.0,
        "cm_size": 26.5
      },
      {
        "eur_size": 42.5,
        "cm_size": 26.5
      },
      {
        "eur_size": 43.0,
        "cm_size": 27.5
      },
      {
        "eur_size": 44.0,
        "cm_size": 28.0
      },
      {
        "eur_size": 44.5,
        "cm_size": 28.0
      },
      {
        "eur_size": 45.0,
        "cm_size": 29.0
      },
      {
        "eur_size": 45.5,
        "cm_size": 29.0
      },
      {
        "eur_size": 46.0,
        "cm_size": 29.5
      },
      {
        "eur_size": 46.5,
        "cm_size": 29.5
      },
      {
        "eur_size": 47.0,
        "cm_size": 30.0
      },
      {
        "eur_size": 47.5,
        "cm_size": 30.0
      },
      {
        "eur_size": 48.0,
        "cm_size": 30.5
      },
      {
        "eur_size": 48.5,
        "cm_size": 30.5
      },
      {
        "eur_size": 49.0,
        "cm_size": 32.7
      },
      {
        "eur_size": 49.5,
        "cm_size": 33.0
      }
    ]
  },
  {
    "name": "New Balance 9060 X Black Cat U9060IMA",
    "price_usd": 99,
    "old_price_usd": 163,
    "url": "https://sneakers.com.ua/usi-tovary/new-balance-9060-x-black-cat-u9060ima",
    "slug": "new-balance-9060-x-black-cat-u9060ima",
    "groupSlug": "new-balance-9060-x-black-cat-u9060ima",
    "appearance_en": "Текстильна сітка, синтетичні накладки, шкіра  New Balance 9060 — ці кросівки є стильним і функціональним взуттям, яке поєднує в собі сучасний дизайн і передові технології. Вони є одними з нових моделей від всесвітньо відомого бренду New Balance, що славиться своєю якістю та комфортом. New Balance 9060 – це взуття, розроблене для тих, хто цінує комфорт, якість та стиль. Вони ідеально підходять для будь-якої активності, від спорту до повсякденного життя. Якщо Ви шукаєте надійну та сучасну пару кро",
    "images_local": [
      "/products/sneakers/new_balance_9060_x_black_cat_u9060ima/1.png",
      "/products/sneakers/new_balance_9060_x_black_cat_u9060ima/2.png",
      "/products/sneakers/new_balance_9060_x_black_cat_u9060ima/3.png",
      "/products/sneakers/new_balance_9060_x_black_cat_u9060ima/4.png",
      "/products/sneakers/new_balance_9060_x_black_cat_u9060ima/5.png"
    ],
    "sizes": [
      {
        "eur_size": 35.0,
        "cm_size": 23.3
      },
      {
        "eur_size": 35.5,
        "cm_size": 23.7
      },
      {
        "eur_size": 36.0,
        "cm_size": 23.0
      },
      {
        "eur_size": 36.5,
        "cm_size": 23.0
      },
      {
        "eur_size": 37.0,
        "cm_size": 23.5
      },
      {
        "eur_size": 37.5,
        "cm_size": 23.5
      },
      {
        "eur_size": 38.0,
        "cm_size": 24.0
      },
      {
        "eur_size": 38.5,
        "cm_size": 24.0
      },
      {
        "eur_size": 39.0,
        "cm_size": 25.0
      },
      {
        "eur_size": 40.0,
        "cm_size": 25.5
      },
      {
        "eur_size": 41.0,
        "cm_size": 26.0
      },
      {
        "eur_size": 42.0,
        "cm_size": 26.5
      },
      {
        "eur_size": 42.5,
        "cm_size": 26.5
      },
      {
        "eur_size": 43.0,
        "cm_size": 27.5
      },
      {
        "eur_size": 44.0,
        "cm_size": 28.0
      },
      {
        "eur_size": 44.5,
        "cm_size": 28.0
      },
      {
        "eur_size": 45.0,
        "cm_size": 29.0
      },
      {
        "eur_size": 45.5,
        "cm_size": 29.0
      },
      {
        "eur_size": 46.0,
        "cm_size": 29.5
      },
      {
        "eur_size": 46.5,
        "cm_size": 29.5
      },
      {
        "eur_size": 47.0,
        "cm_size": 30.0
      },
      {
        "eur_size": 47.5,
        "cm_size": 30.0
      },
      {
        "eur_size": 48.0,
        "cm_size": 30.5
      },
      {
        "eur_size": 48.5,
        "cm_size": 30.5
      },
      {
        "eur_size": 49.0,
        "cm_size": 32.7
      },
      {
        "eur_size": 49.5,
        "cm_size": 33.0
      }
    ]
  },
  {
    "name": "Adidas Terrex Skychaser Tech Gore-Tex Khaki Black White",
    "price_usd": 87,
    "old_price_usd": 149,
    "url": "https://sneakers.com.ua/usi-tovary/adidas-terrex-skychaser-tech-gore-tex-khaki-black-white",
    "slug": "adidas-terrex-skychaser-tech-gore-tex-khaki-black-white",
    "groupSlug": "adidas-terrex-skychaser-tech-gore-tex-khaki",
    "appearance_en": "Зовні:верх кросівок виконаний з водонепроникної та дихаючої тканини Gore-Tex; Всередині: м яка текстильна підкладка, анатомічна дихаюча устілка та фіксація пʼятки; Підошва: Lightstrike яка забезпечує амортизацію та зчеплення; Сезонність: може використовуватись протягом всього року в залежності від погодних умов; Виробник: Adidas.  Усі товари доставляються виключно за допомогою компанії «НОВА ПОШТА», жодних інших варіантів доставки — не передбачено! Оплата здійснюється при отриманні, після огляду",
    "images_local": [
      "/products/sneakers/adidas_terrex_skychaser_tech_gore_tex_khaki_black_white/1.png",
      "/products/sneakers/adidas_terrex_skychaser_tech_gore_tex_khaki_black_white/2.png",
      "/products/sneakers/adidas_terrex_skychaser_tech_gore_tex_khaki_black_white/3.png",
      "/products/sneakers/adidas_terrex_skychaser_tech_gore_tex_khaki_black_white/4.png",
      "/products/sneakers/adidas_terrex_skychaser_tech_gore_tex_khaki_black_white/5.png"
    ],
    "sizes": [
      {
        "eur_size": 35.0,
        "cm_size": 23.3
      },
      {
        "eur_size": 35.5,
        "cm_size": 23.7
      },
      {
        "eur_size": 36.0,
        "cm_size": 23.0
      },
      {
        "eur_size": 36.5,
        "cm_size": 23.0
      },
      {
        "eur_size": 37.0,
        "cm_size": 23.5
      },
      {
        "eur_size": 37.5,
        "cm_size": 23.5
      },
      {
        "eur_size": 38.0,
        "cm_size": 24.0
      },
      {
        "eur_size": 38.5,
        "cm_size": 24.0
      },
      {
        "eur_size": 39.0,
        "cm_size": 25.0
      },
      {
        "eur_size": 40.0,
        "cm_size": 25.5
      },
      {
        "eur_size": 41.0,
        "cm_size": 26.0
      },
      {
        "eur_size": 42.0,
        "cm_size": 26.5
      },
      {
        "eur_size": 42.5,
        "cm_size": 26.5
      },
      {
        "eur_size": 43.0,
        "cm_size": 27.5
      },
      {
        "eur_size": 44.0,
        "cm_size": 28.0
      },
      {
        "eur_size": 44.5,
        "cm_size": 28.0
      },
      {
        "eur_size": 45.0,
        "cm_size": 29.0
      },
      {
        "eur_size": 45.5,
        "cm_size": 29.0
      },
      {
        "eur_size": 46.0,
        "cm_size": 29.5
      },
      {
        "eur_size": 46.5,
        "cm_size": 29.5
      },
      {
        "eur_size": 47.0,
        "cm_size": 30.0
      },
      {
        "eur_size": 47.5,
        "cm_size": 30.0
      },
      {
        "eur_size": 48.0,
        "cm_size": 30.5
      },
      {
        "eur_size": 48.5,
        "cm_size": 30.5
      },
      {
        "eur_size": 49.0,
        "cm_size": 32.7
      },
      {
        "eur_size": 49.5,
        "cm_size": 33.0
      }
    ]
  },
  {
    "name": "Nike Air Force 1 Low x Supreme Beige Brown",
    "price_usd": 107,
    "old_price_usd": 164,
    "url": "https://sneakers.com.ua/usi-tovary/nike-air-force-1-low-x-supreme-beige-brown",
    "slug": "nike-air-force-1-low-x-supreme-beige-brown",
    "groupSlug": "nike-air-force-1-low-x-supreme",
    "appearance_en": "класика та надійність, асболютно зносостійка шкіра та міцна строчка, за взуттям легко доглядати, кросівки дуже живучі. Підійдуть підь будь-який гардероб, відрізняються підвищенним комфортом. Удосконалений дизайн та покращена якість дозволяють використовувати air force будь-де: для спорту, для щоденних прогулянок, для баскетболу чи скейтбордингу, для чоловіків та для жінок, для молоді та для літніх людей — ці форси реально найкращі у світі.",
    "images_local": [
      "/products/sneakers/nike_air_force_1_low_x_supreme_beige_brown/1.png",
      "/products/sneakers/nike_air_force_1_low_x_supreme_beige_brown/2.png",
      "/products/sneakers/nike_air_force_1_low_x_supreme_beige_brown/3.png",
      "/products/sneakers/nike_air_force_1_low_x_supreme_beige_brown/4.png",
      "/products/sneakers/nike_air_force_1_low_x_supreme_beige_brown/5.png"
    ],
    "sizes": [
      {
        "eur_size": 35.0,
        "cm_size": 23.3
      },
      {
        "eur_size": 35.5,
        "cm_size": 23.7
      },
      {
        "eur_size": 36.0,
        "cm_size": 23.0
      },
      {
        "eur_size": 36.5,
        "cm_size": 23.0
      },
      {
        "eur_size": 37.0,
        "cm_size": 23.5
      },
      {
        "eur_size": 37.5,
        "cm_size": 23.5
      },
      {
        "eur_size": 38.0,
        "cm_size": 24.0
      },
      {
        "eur_size": 38.5,
        "cm_size": 24.0
      },
      {
        "eur_size": 39.0,
        "cm_size": 25.0
      },
      {
        "eur_size": 40.0,
        "cm_size": 25.5
      },
      {
        "eur_size": 41.0,
        "cm_size": 26.0
      },
      {
        "eur_size": 42.0,
        "cm_size": 26.5
      },
      {
        "eur_size": 42.5,
        "cm_size": 26.5
      },
      {
        "eur_size": 43.0,
        "cm_size": 27.5
      },
      {
        "eur_size": 44.0,
        "cm_size": 28.0
      },
      {
        "eur_size": 44.5,
        "cm_size": 28.0
      },
      {
        "eur_size": 45.0,
        "cm_size": 29.0
      },
      {
        "eur_size": 45.5,
        "cm_size": 29.0
      },
      {
        "eur_size": 46.0,
        "cm_size": 29.5
      },
      {
        "eur_size": 46.5,
        "cm_size": 29.5
      },
      {
        "eur_size": 47.0,
        "cm_size": 30.0
      },
      {
        "eur_size": 47.5,
        "cm_size": 30.0
      },
      {
        "eur_size": 48.0,
        "cm_size": 30.5
      },
      {
        "eur_size": 48.5,
        "cm_size": 30.5
      },
      {
        "eur_size": 49.0,
        "cm_size": 32.7
      },
      {
        "eur_size": 49.5,
        "cm_size": 33.0
      }
    ]
  },
  {
    "name": "Nike SB Dunk Low Beige Green",
    "price_usd": 100,
    "old_price_usd": 155,
    "url": "https://sneakers.com.ua/usi-tovary/nike-sb-dunk-low-beige-green",
    "slug": "nike-sb-dunk-low-beige-green",
    "groupSlug": "nike-sb-dunk-low",
    "appearance_en": "Зовні: взуття виконано з міцної шкіри, скрізь присутня строчка; Всередині: м яка текстильна підкладка, анатомічна дихаюча устілка; Підошва: з піноматеріалу, прихований балон для амортизації за технологією гарантує комфорт та безпеку, підошви прошиті та проклеєні за сучасними технологіями із використанням високих температур і тиску. Підмітка з натуральної резини з чіпким візерунком протектора гарантує зчеплення з будь-якими поверхнями; Сезонність: універсальна; Виробник: В’єтнам.  Доставка: налож",
    "images_local": [
      "/products/sneakers/nike_sb_dunk_low_beige_green/1.png",
      "/products/sneakers/nike_sb_dunk_low_beige_green/2.png",
      "/products/sneakers/nike_sb_dunk_low_beige_green/3.png",
      "/products/sneakers/nike_sb_dunk_low_beige_green/4.png",
      "/products/sneakers/nike_sb_dunk_low_beige_green/5.png"
    ],
    "sizes": [
      {
        "eur_size": 35.0,
        "cm_size": 23.3
      },
      {
        "eur_size": 35.5,
        "cm_size": 23.7
      },
      {
        "eur_size": 36.0,
        "cm_size": 23.0
      },
      {
        "eur_size": 36.5,
        "cm_size": 23.0
      },
      {
        "eur_size": 37.0,
        "cm_size": 23.5
      },
      {
        "eur_size": 37.5,
        "cm_size": 23.5
      },
      {
        "eur_size": 38.0,
        "cm_size": 24.0
      },
      {
        "eur_size": 38.5,
        "cm_size": 24.0
      },
      {
        "eur_size": 39.0,
        "cm_size": 25.0
      },
      {
        "eur_size": 40.0,
        "cm_size": 25.5
      },
      {
        "eur_size": 41.0,
        "cm_size": 26.0
      },
      {
        "eur_size": 42.0,
        "cm_size": 26.5
      },
      {
        "eur_size": 42.5,
        "cm_size": 26.5
      },
      {
        "eur_size": 43.0,
        "cm_size": 27.5
      },
      {
        "eur_size": 44.0,
        "cm_size": 28.0
      },
      {
        "eur_size": 44.5,
        "cm_size": 28.0
      },
      {
        "eur_size": 45.0,
        "cm_size": 29.0
      },
      {
        "eur_size": 45.5,
        "cm_size": 29.0
      },
      {
        "eur_size": 46.0,
        "cm_size": 29.5
      },
      {
        "eur_size": 46.5,
        "cm_size": 29.5
      },
      {
        "eur_size": 47.0,
        "cm_size": 30.0
      },
      {
        "eur_size": 47.5,
        "cm_size": 30.0
      },
      {
        "eur_size": 48.0,
        "cm_size": 30.5
      },
      {
        "eur_size": 48.5,
        "cm_size": 30.5
      },
      {
        "eur_size": 49.0,
        "cm_size": 32.7
      },
      {
        "eur_size": 49.5,
        "cm_size": 33.0
      }
    ]
  }
]